km/__init__.py
km/__main__.py
km/km.py
km/argparser/__init__.py
km/argparser/common.py
km/argparser/find_mutation.py
km/argparser/find_report.py
km/argparser/linear_kmin.py
km/argparser/min_cov.py
km/tests/__init__.py
km/tests/test_main.py
km/tools/__init__.py
km/tools/find_mutation.py
km/tools/find_report.py
km/tools/linear_kmin.py
km/tools/min_cov.py
km/utils/Graph.py
km/utils/Jellyfish.py
km/utils/MutationFinder.py
km/utils/PathQuant.py
km/utils/Sequence.py
km/utils/__init__.py
km/utils/common.py
km_walk-2.2.2.dist-info/LICENSE
km_walk-2.2.2.dist-info/METADATA
km_walk-2.2.2.dist-info/WHEEL
km_walk-2.2.2.dist-info/entry_points.txt
km_walk-2.2.2.dist-info/top_level.txt
km_walk-2.2.2.dist-info/RECORD
