Metadata-Version: 2.1
Name: km-walk
Version: 2.2.2
Summary: A software for RNA-seq investigation using k-mer decomposition
Author-email: Albert Feghaly <albert.feghaly@umontreal.ca>, Eric Audemard <eric.audemard@umontreal.ca>, Patrick Gendron <patrick.gendron@umontreal.ca>, Sebastien Lemieux <s.lemieux@umontreal.ca>
License: MIT
Project-URL: Repository, https://github.com/iric-soft/km
Keywords: k-mer,RNA-seq,variant,sequencing
Classifier: Development Status :: 5 - Production/Stable
Classifier: Intended Audience :: Science/Research
Classifier: Intended Audience :: Developers
Classifier: Intended Audience :: Healthcare Industry
Classifier: Topic :: Scientific/Engineering :: Bio-Informatics
Classifier: Topic :: Software Development
Classifier: Topic :: Software Development :: Build Tools
Classifier: Programming Language :: Python
Classifier: Programming Language :: Python :: 3
Classifier: Programming Language :: Python :: 3.8
Classifier: Programming Language :: Python :: 3.9
Classifier: Programming Language :: Python :: 3.10
Classifier: Programming Language :: Python :: 3.11
Classifier: Programming Language :: Python :: 3.12
Classifier: Operating System :: MacOS
Classifier: Operating System :: POSIX :: Linux
Classifier: License :: OSI Approved :: MIT License
Classifier: Natural Language :: English
Requires-Python: >=3.8
License-File: LICENSE
Requires-Dist: numpy >=1.18.1
Requires-Dist: matplotlib >=3.3.4
Requires-Dist: pyjellyfish >=1.3.0
Requires-Dist: pytest >=6.2.0
Provides-Extra: test
Requires-Dist: pytest ; extra == 'test'
